apthesaurus/__init__.py
apthesaurus/api/__init__.py
apthesaurus/api/add/__init__.py
apthesaurus/api/search/__init__.py
apthesaurus/version/__init__.py
apthesaurus-22.2.1.dist-info/METADATA
apthesaurus-22.2.1.dist-info/WHEEL
apthesaurus-22.2.1.dist-info/entry_points.txt
apthesaurus-22.2.1.dist-info/top_level.txt
apthesaurus-22.2.1.dist-info/RECORD
