Metadata-Version: 2.1
Name: apthesaurus
Version: 22.2.1
Summary: UNKNOWN
Author: Stefan Heitmüller
Author-email: stefan.heitmueller@root360.de
License: MIT
Platform: UNKNOWN
Requires-Python: ~=3.8
Requires-Dist: sanic (==21.12.1)
Requires-Dist: sanic-ext (==22.1.2)
